nice_errors/__init__.py
nice_errors/__main__.py
nice_errors-1.1.0.dist-info/licenses/LICENSE
nice_errors-1.1.0.dist-info/METADATA
nice_errors-1.1.0.dist-info/WHEEL
nice_errors-1.1.0.dist-info/top_level.txt
nice_errors-1.1.0.dist-info/RECORD
