Metadata-Version: 2.4
Name: nice-errors
Version: 1.1.0
Summary: Nice error messages for Python
Author: ProgMEM-CC
License-Expression: AGPL-3.0-only
Project-URL: Homepage, https://github.com/ProgMEM-CC/nice-errors
Project-URL: Issues, https://github.com/ProgMEM-CC/nice-errors/issues
Classifier: Programming Language :: Python :: 3
Classifier: Operating System :: OS Independent
Requires-Python: >=3.9
License-File: LICENSE
Requires-Dist: colorama
Dynamic: license-file
